pyclimacell/__init__.py
pyclimacell/const.py
pyclimacell/exceptions.py
pyclimacell/helpers.py
pyclimacell/pyclimacell.py
pyclimacell-0.18.2.dist-info/AUTHORS.rst
pyclimacell-0.18.2.dist-info/LICENSE
pyclimacell-0.18.2.dist-info/METADATA
pyclimacell-0.18.2.dist-info/WHEEL
pyclimacell-0.18.2.dist-info/top_level.txt
pyclimacell-0.18.2.dist-info/RECORD
