Metadata-Version: 2.1
Name: pyclimacell
Version: 0.18.2
Summary: Async Python3.7+ package to access the ClimaCell API
Home-page: https://github.com/raman325/pyclimacell
Author: raman325
Author-email: 7243222+raman325@users.noreply.github.com
License: MIT license
Keywords: pyclimacell
Platform: UNKNOWN
Classifier: Development Status :: 2 - Pre-Alpha
Classifier: Intended Audience :: Developers
Classifier: License :: OSI Approved :: MIT License
Classifier: Natural Language :: English
Classifier: Programming Language :: Python :: 3
Classifier: Programming Language :: Python :: 3.6
Classifier: Programming Language :: Python :: 3.7
Classifier: Programming Language :: Python :: 3.8
Requires-Python: >=3.6
Requires-Dist: aiohttp (>=3.6.2)
Requires-Dist: pytz
